cli/main.py
demo/example_run_altanalyze3.py
docs/conf.py
subsplice/__init__.py
subsplice/correlation_depletion.py
subsplice/determine_rank.py
subsplice/feature_selection.py
subsplice/linear_svm.py
subsplice/main_functions.py
subsplice/median_impute.py
subsplice/metadata_analysis.py
subsplice/preprocess.py
subsplice/remove_redundancy.py
subsplice/round_wrapper.py
subsplice/run_nmf.py
subsplice/visualizations.py
subsplice-0.0.0.dist-info/licenses/LICENSE
test/evaluations_all.py
test/max_f1_score.py
test/record_times_across_feats_full_dataset_fast_corr.py
subsplice-0.0.0.dist-info/METADATA
subsplice-0.0.0.dist-info/WHEEL
subsplice-0.0.0.dist-info/top_level.txt
subsplice-0.0.0.dist-info/RECORD
